{"name":"build-javascript","namedChunkGroups":{"polyfill":{"name":"polyfill","assets":[{"name":"webpack-runtime-72d10dc3496fff41a8c3.js","size":4397},{"name":"polyfill-c9fa82aa5b1f9c65f078.js","size":85039}],"filteredAssets":0,"assetsSize":89436,"filteredAuxiliaryAssets":2,"auxiliaryAssetsSize":228695},"app":{"name":"app","assets":[{"name":"webpack-runtime-72d10dc3496fff41a8c3.js","size":4397},{"name":"framework-54a02ad02f23896e401c.js","size":140566},{"name":"app-b2dfb57b874638e3ca35.js","size":65493}],"filteredAssets":0,"assetsSize":210456,"filteredAuxiliaryAssets":3,"auxiliaryAssetsSize":626709},"component---src-pages-404-js":{"name":"component---src-pages-404-js","assets":[{"name":"component---src-pages-404-js-237bb37ac1162706cca0.js","size":1420}],"filteredAssets":0,"assetsSize":1420,"filteredAuxiliaryAssets":1,"auxiliaryAssetsSize":2890},"component---src-pages-index-js":{"name":"component---src-pages-index-js","assets":[{"name":"styles.a5680e227420919e1451.css","size":597},{"name":"5e2a4920-8128e1a0db4d274f8980.js","size":520},{"name":"component---src-pages-index-js-35c054ff0180367bb341.js","size":5616}],"filteredAssets":0,"assetsSize":6733,"filteredAuxiliaryAssets":2,"auxiliaryAssetsSize":236160}},"assetsByChunkName":{"polyfill":["webpack-runtime-72d10dc3496fff41a8c3.js","polyfill-c9fa82aa5b1f9c65f078.js"],"app":["webpack-runtime-72d10dc3496fff41a8c3.js","framework-54a02ad02f23896e401c.js","app-b2dfb57b874638e3ca35.js"],"component---src-pages-404-js":["component---src-pages-404-js-237bb37ac1162706cca0.js"],"component---src-pages-index-js":["styles.a5680e227420919e1451.css","5e2a4920-8128e1a0db4d274f8980.js","component---src-pages-index-js-35c054ff0180367bb341.js"]},"childAssetsByChunkName":{}}